RxUnit/RxUnit.vhd
library IEEE;
use IEEE.std_logic_1164.all;

entity RxUnit is
  port (
    clk, reset       : in  std_logic;
    enable           : in  std_logic;
    rd               : in  std_logic;
    rxd              : in  std_logic;
    data             : out std_logic_vector(7 downto 0);
    Ferr, OErr, DRdy : out std_logic);
end RxUnit;

architecture behavorial of RxUnit is

signal tmpclk : std_logic; -- Signaux intermédiaires de clk et de rxd venant du Proc_cpt16 vers le Proc_ctrlReception
signal tmprxd : std_logic;
-- Etat du process cpt16
type t_etat_cpt is (Idle, cpt1, cpt2); 
-- Etat de base : Idle, quand Rxd passe à 0, on commence la réception (11 fois cpt1 et cpt2 pour réceptionner toute la trame)
-- Cpt1 : Première phase de comptage de 8 enable, on affcte tmpclk et tmprxd à la fin du comptage.
-- Cpt2 : Deuxième phase de comptage, si on a vu toute la trame passée à la fin de cette phase
-- on va soit retourné en idle, soit relancé la réception d'une trame avec cpt1.
signal etatCpt : t_etat_cpt;

begin

Proc_Cpt16 : process(enable)
variable cpt : natural; -- Permet de compter les fronts d'enable
variable cptTrame : natural; -- Permet de compter les bits reçut jusqu'à la fin d'une trame.
-- Taille d'une trame : 1 bit start + 8 bit donnée + 1 parité + 1 stop = 11 bits.
begin 
	if(reset = 0) then
		etatCpt <= Idle;
	elsif(rising_edge(enable)) then
		case etatCpt is 
		when Idle => 
			tmpclk <= 0;
			tmprxd <= 1;
			cpt := 8;
			cptTrame := 11;
			if(rxd = '0') then 
				etatCpt <= cpt1;
			end if;
			
		when cpt1 =>
			cpt := cpt - 1;
			if(cpt = 0) then 
				etatCpt <= cpt2;
				tmpclk <= '1';
				tmprxd <= rxd;
				cpt := 8;
			end if;
			
		when cpt2 =>
		if(tmpclk = '1') then -- On rabaisse le signal tmpclk. 
			tmpclk <= '0';
		end if;
		
		cpt := cpt - 1;
		
		if(cpt = 0) then -- Fin du comptage, on repasse à cpt1 en décrémenter le nombre de bits encore à recevoir.
			cptTrame := cptTrame - 1;
			etatCpt <= cpt1;
		end if;
		
		if(cptTrame = 0) then -- Si on a reçu toute la trame (11 bits)
			cptTrame := 11;
			if(rxd = '1') then -- On va soit retourner à Cpt1 si une autre transmission suit, c'est à dire 
				etatCpt <= Idle; -- si on recoit un autre bit de start (rxd = '0') dès la fin de la trame.
			end if; -- Ou si Rxd = '1', on va alors repasser en idle qui attendra la réception d'une future trame.
		end if; 
	end if;
end process;

Proc_ctrlReception : process(clk)

variable regRecep : std_logic_vector(10 downto 0); -- Le registre sauvegardant la réception des 11 bits d'une trame.
variable cptBit : natural; -- Numérotation du bit qui est en réception.

type t_etat_recep is (Idle, Reception); 

signal etatRecep : t_etat_cpt;

begin 
	if(reset = 0) then
		etatRecep <= Idle;
	elsif(rising_edge(clk)) then
		case etatRecep is 
		when Idle =>
			DRdy <= '0';
			Ferr <= '0';
			OErr <= '0';
			if(tmpclk = '1') then
				etatRecep <= Reception;
				cptBit := 11;
			end if;	
				
		when Reception =>
			if(tmpclk = '1') then 
				cptBit := cptBit - 1;
				regRecep(cptBit) := rxdtmp;
				-- Bit de poids fort ou faible en premier ???? 
				if(cptBit = 0) then 
				-- Verif des bits de stop/parité
				-- Envoi de la data si c'est bon.
				
	end if;
end process; 

end behavorial;

RxUnit/RxTestTrame.vhd
--------------------------------------------------------------------------------
-- Company: 
-- Engineer:
--
-- Create Date:   15:05:35 12/10/2019
-- Design Name:   
-- Module Name:   /home/jdides/S1/Archi/UART/RxUnit/RxTestOk.vhd
-- Project Name:  UART
-- Target Device:  
-- Tool versions:  
-- Description:   
-- 
-- VHDL Test Bench Created by ISE for module: RxUnit
-- 
-- Dependencies:
-- 
-- Revision:
-- Revision 0.01 - File Created
-- Additional Comments:
--
-- Notes: 
-- This testbench has been automatically generated using types std_logic and
-- std_logic_vector for the ports of the unit under test.  Xilinx recommends
-- that these types always be used for the top-level I/O of a design in order
-- to guarantee that the testbench will bind correctly to the post-implementation 
-- simulation model.
--------------------------------------------------------------------------------
LIBRARY ieee;
USE ieee.std_logic_1164.ALL;
 
-- Uncomment the following library declaration if using
-- arithmetic functions with Signed or Unsigned values
--USE ieee.numeric_std.ALL;
 
ENTITY RxTestTrame IS
END RxTestTrame;
 
ARCHITECTURE behavior OF RxTestTrame IS 
 
    -- Component Declaration for the Unit Under Test (UUT)
 
    COMPONENT RxUnit
    PORT(
         clk : IN  std_logic;
         reset : IN  std_logic;
         enable : IN  std_logic;
         rd : IN  std_logic;
         rxd : IN  std_logic;
         data : OUT  std_logic_vector(7 downto 0);
         FErr : OUT  std_logic;
         OErr : OUT  std_logic;
         DRdy : OUT  std_logic
        );
    END COMPONENT;
    

   --Inputs
   signal clk : std_logic := '0';
   signal reset : std_logic := '0';
   signal enable : std_logic := '0';
   signal rd : std_logic := '0';
   signal rxd : std_logic := '0';

 	--Outputs
   signal data : std_logic_vector(7 downto 0);
   signal FErr : std_logic;
   signal OErr : std_logic;
   signal DRdy : std_logic;

   -- Clock period definitions
   constant clk_period : time := 10 ns;
 
BEGIN
 
	-- Instantiate the Unit Under Test (UUT)
   uut: RxUnit PORT MAP (
          clk => clk,
          reset => reset,
          enable => enable,
          rd => rd,
          rxd => rxd,
          data => data,
          FErr => FErr,
          OErr => OErr,
          DRdy => DRdy
        );

   -- Clock process definitions On met enable deux fois plus lent que la clk
   clk_process :process
   begin
		clk <= '0';
		enable <= '0';
		wait for clk_period/2;
		clk <= '1';
		wait for clk_period/2;
		enable <= '1';

		clk <= '0';
		wait for clk_period/2;
		clk <= '1';
		wait for clk_period/2;
   end process;
 

   -- Stimulus process
   stim_proc: process
   begin		
		reset <= '0';
		rxd <= '0';
      -- hold reset state for 100 ns.
      wait for 100 ns;	
		reset <= '1';
		wait for clk_period*4;
		rxd <= '1';
		wait for clk_period*10;
		rxd <= '0';
		wait for clk_period*64;
		rxd <= '1';
		wait for clk_period*32;
		rxd <= '0';
		wait for clk_period*32;
		rxd <= '1';
		wait for clk_period*32;
		rxd <= '0';
		wait for clk_period*32;
		rxd <= '1';
		wait for clk_period*32;
		rxd <= '0';
		wait for clk_period*32;
		rxd <= '1';
		wait for clk_period*32;
		rxd <= '0';
		wait for clk_period*32;
		rxd <= '0'; -- Erreur dans le bit de stop.
		wait for clk_period*32;
		rxd <= '1';
		
		wait until DRdy = '1';
		wait until DRdy = '0';
		rd <= '1';
		wait for clk_period*2;
		rd <= '0';
      -- insert stimulus here 

      wait;
   end process;

END;

RxUnit/Simulations/TestTrame.vcd
$date
   Mon Dec 16 11:04:39 2019
$end
$version
  P.20131013
$end
$timescale
  1ps
$end
$scope module rxtesttrame $end
$var wire 1 1 clk $end
$var wire 1 2 reset $end
$var wire 1 3 enable $end
$var wire 1 4 rd $end
$var wire 1 5 rxd $end
$var wire 1 = data [7] $end
$var wire 1 < data [6] $end
$var wire 1 ; data [5] $end
$var wire 1 : data [4] $end
$var wire 1 9 data [3] $end
$var wire 1 8 data [2] $end
$var wire 1 7 data [1] $end
$var wire 1 6 data [0] $end
$var wire 1 > ferr $end
$var wire 1 ? oerr $end
$var wire 1 @ drdy $end
$scope module uut $end
$var wire 1 1 clk $end
$var wire 1 2 reset $end
$var wire 1 3 enable $end
$var wire 1 4 rd $end
$var wire 1 5 rxd $end
$var wire 1 = data [7] $end
$var wire 1 < data [6] $end
$var wire 1 ; data [5] $end
$var wire 1 : data [4] $end
$var wire 1 9 data [3] $end
$var wire 1 8 data [2] $end
$var wire 1 7 data [1] $end
$var wire 1 6 data [0] $end
$var wire 1 > ferr $end
$var wire 1 ? oerr $end
$var wire 1 @ drdy $end
$var wire 1 A tmpclk $end
$var wire 1 B tmprxd $end
$upscope $end
$upscope $end
$enddefinitions $end
#0
$dumpvars
02
01
03
04
05
x=
x<
x;
x:
x9
x8
x7
x6
0>
0?
0@
xA
xB
$end
#5000
11
#10000
01
13
#15000
11
#20000
01
03
#25000
11
#30000
01
13
#35000
11
#40000
01
03
#45000
11
#50000
01
13
#55000
11
#60000
01
03
#65000
11
#70000
01
13
#75000
11
#80000
01
03
#85000
11
#90000
01
13
#95000
11
#100000
12
01
03
#105000
11
#110000
01
13
0A
1B
#115000
11
#120000
01
03
#125000
11
#130000
01
13
#135000
11
#140000
01
03
15
#145000
11
#150000
01
13
#155000
11
#160000
01
03
#165000
11
#170000
01
13
#175000
11
#180000
01
03
#185000
11
#190000
01
13
#195000
11
#200000
01
03
#205000
11
#210000
01
13
#215000
11
#220000
01
03
#225000
11
#230000
01
13
#235000
11
#240000
01
03
05
#245000
11
#250000
01
13
#255000
11
#260000
01
03
#265000
11
#270000
01
13
1A
0B
#275000
11
#280000
01
03
#285000
11
#290000
01
13
0A
#295000
11
#300000
01
03
#305000
11
#310000
01
13
#315000
11
#320000
01
03
#325000
11
#330000
01
13
#335000
11
#340000
01
03
#345000
11
#350000
01
13
#355000
11
#360000
01
03
#365000
11
#370000
01
13
#375000
11
#380000
01
03
#385000
11
#390000
01
13
#395000
11
#400000
01
03
#405000
11
#410000
01
13
#415000
11
#420000
01
03
#425000
11
#430000
01
13
#435000
11
#440000
01
03
#445000
11
#450000
01
13
#455000
11
#460000
01
03
#465000
11
#470000
01
13
#475000
11
#480000
01
03
#485000
11
#490000
01
13
#495000
11
#500000
01
03
#505000
11
#510000
01
13
#515000
11
#520000
01
03
#525000
11
#530000
01
13
#535000
11
#540000
01
03
#545000
11
#550000
01
13
#555000
11
#560000
01
03
#565000
11
#570000
01
13
#575000
11
#580000
01
03
#585000
11
#590000
01
13
1A
#595000
11
#600000
01
03
#605000
11
#610000
01
13
0A
#615000
11
#620000
01
03
#625000
11
#630000
01
13
#635000
11
#640000
01
03
#645000
11
#650000
01
13
#655000
11
#660000
01
03
#665000
11
#670000
01
13
#675000
11
#680000
01
03
#685000
11
#690000
01
13
#695000
11
#700000
01
03
#705000
11
#710000
01
13
#715000
11
#720000
01
03
#725000
11
#730000
01
13
#735000
11
#740000
01
03
#745000
11
#750000
01
13
#755000
11
#760000
01
03
#765000
11
#770000
01
13
#775000
11
#780000
01
03
#785000
11
#790000
01
13
#795000
11
#800000
01
03
#805000
11
#810000
01
13
#815000
11
#820000
01
03
#825000
11
#830000
01
13
#835000
11
#840000
01
03
#845000
11
#850000
01
13
#855000
11
#860000
01
03
#865000
11
#870000
01
13
#875000
11
#880000
01
03
15
#885000
11
#890000
01
13
#895000
11
#900000
01
03
#905000
11
#910000
01
13
1A
1B
#915000
11
#920000
01
03
#925000
11
#930000
01
13
0A
#935000
11
#940000
01
03
#945000
11
#950000
01
13
#955000
11
#960000
01
03
#965000
11
#970000
01
13
#975000
11
#980000
01
03
#985000
11
#990000
01
13
#995000
11
#1000000
01
03
#1005000
11
#1010000
01
13
#1015000
11
#1020000
01
03
#1025000
11
#1030000
01
13
#1035000
11
#1040000
01
03
#1045000
11
#1050000
01
13
#1055000
11
#1060000
01
03
#1065000
11
#1070000
01
13
#1075000
11
#1080000
01
03
#1085000
11
#1090000
01
13
#1095000
11
#1100000
01
03
#1105000
11
#1110000
01
13
#1115000
11
#1120000
01
03
#1125000
11
#1130000
01
13
#1135000
11
#1140000
01
03
#1145000
11
#1150000
01
13
#1155000
11
#1160000
01
03
#1165000
11
#1170000
01
13
#1175000
11
#1180000
01
03
#1185000
11
#1190000
01
13
#1195000
11
#1200000
01
03
05
#1205000
11
#1210000
01
13
#1215000
11
#1220000
01
03
#1225000
11
#1230000
01
13
1A
0B
#1235000
11
#1240000
01
03
#1245000
11
#1250000
01
13
0A
#1255000
11
#1260000
01
03
#1265000
11
#1270000
01
13
#1275000
11
#1280000
01
03
#1285000
11
#1290000
01
13
#1295000
11
#1300000
01
03
#1305000
11
#1310000
01
13
#1315000
11
#1320000
01
03
#1325000
11
#1330000
01
13
#1335000
11
#1340000
01
03
#1345000
11
#1350000
01
13
#1355000
11
#1360000
01
03
#1365000
11
#1370000
01
13
#1375000
11
#1380000
01
03
#1385000
11
#1390000
01
13
#1395000
11
#1400000
01
03
#1405000
11
#1410000
01
13
#1415000
11
#1420000
01
03
#1425000
11
#1430000
01
13
#1435000
11
#1440000
01
03
#1445000
11
#1450000
01
13
#1455000
11
#1460000
01
03
#1465000
11
#1470000
01
13
#1475000
11
#1480000
01
03
#1485000
11
#1490000
01
13
#1495000
11
#1500000
01
03
#1505000
11
#1510000
01
13
#1515000
11
#1520000
01
03
15
#1525000
11
#1530000
01
13
#1535000
11
#1540000
01
03
#1545000
11
#1550000
01
13
1A
1B
#1555000
11
#1560000
01
03
#1565000
11
#1570000
01
13
0A
#1575000
11
#1580000
01
03
#1585000
11
#1590000
01
13
#1595000
11
#1600000
01
03
#1605000
11
#1610000
01
13
#1615000
11
#1620000
01
03
#1625000
11
#1630000
01
13
#1635000
11
#1640000
01
03
#1645000
11
#1650000
01
13
#1655000
11
#1660000
01
03
#1665000
11
#1670000
01
13
#1675000
11
#1680000
01
03
#1685000
11
#1690000
01
13
#1695000
11
#1700000
01
03
#1705000
11
#1710000
01
13
#1715000
11
#1720000
01
03
#1725000
11
#1730000
01
13
#1735000
11
#1740000
01
03
#1745000
11
#1750000
01
13
#1755000
11
#1760000
01
03
#1765000
11
#1770000
01
13
#1775000
11
#1780000
01
03
#1785000
11
#1790000
01
13
#1795000
11
#1800000
01
03
#1805000
11
#1810000
01
13
#1815000
11
#1820000
01
03
#1825000
11
#1830000
01
13
#1835000
11
#1840000
01
03
05
#1845000
11
#1850000
01
13
#1855000
11
#1860000
01
03
#1865000
11
#1870000
01
13
1A
0B
#1875000
11
#1880000
01
03
#1885000
11
#1890000
01
13
0A
#1895000
11
#1900000
01
03
#1905000
11
#1910000
01
13
#1915000
11
#1920000
01
03
#1925000
11
#1930000
01
13
#1935000
11
#1940000
01
03
#1945000
11
#1950000
01
13
#1955000
11
#1960000
01
03
#1965000
11
#1970000
01
13
#1975000
11
#1980000
01
03
#1985000
11
#1990000
01
13
#1995000
11
#2000000
01
03
#2005000
11
#2010000
01
13
#2015000
11
#2020000
01
03
#2025000
11
#2030000
01
13
#2035000
11
#2040000
01
03
#2045000
11
#2050000
01
13
#2055000
11
#2060000
01
03
#2065000
11
#2070000
01
13
#2075000
11
#2080000
01
03
#2085000
11
#2090000
01
13
#2095000
11
#2100000
01
03
#2105000
11
#2110000
01
13
#2115000
11
#2120000
01
03
#2125000
11
#2130000
01
13
#2135000
11
#2140000
01
03
#2145000
11
#2150000
01
13
#2155000
11
#2160000
01
03
15
#2165000
11
#2170000
01
13
#2175000
11
#2180000
01
03
#2185000
11
#2190000
01
13
1A
1B
#2195000
11
#2200000
01
03
#2205000
11
#2210000
01
13
0A
#2215000
11
#2220000
01
03
#2225000
11
#2230000
01
13
#2235000
11
#2240000
01
03
#2245000
11
#2250000
01
13
#2255000
11
#2260000
01
03
#2265000
11
#2270000
01
13
#2275000
11
#2280000
01
03
#2285000
11
#2290000
01
13
#2295000
11
#2300000
01
03
#2305000
11
#2310000
01
13
#2315000
11
#2320000
01
03
#2325000
11
#2330000
01
13
#2335000
11
#2340000
01
03
#2345000
11
#2350000
01
13
#2355000
11
#2360000
01
03
#2365000
11
#2370000
01
13
#2375000
11
#2380000
01
03
#2385000
11
#2390000
01
13
#2395000
11
#2400000
01
03
#2405000
11
#2410000
01
13
#2415000
11
#2420000
01
03
#2425000
11
#2430000
01
13
#2435000
11
#2440000
01
03
#2445000
11
#2450000
01
13
#2455000
11
#2460000
01
03
#2465000
11
#2470000
01
13
#2475000
11
#2480000
01
03
05
#2485000
11
#2490000
01
13
#2495000
11
#2500000
01
03
#2505000
11
#2510000
01
13
1A
0B
#2515000
11
#2520000
01
03
#2525000
11
#2530000
01
13
0A
#2535000
11
#2540000
01
03
#2545000
11
#2550000
01
13
#2555000
11
#2560000
01
03
#2565000
11
#2570000
01
13
#2575000
11
#2580000
01
03
#2585000
11
#2590000
01
13
#2595000
11
#2600000
01
03
#2605000
11
#2610000
01
13
#2615000
11
#2620000
01
03
#2625000
11
#2630000
01
13
#2635000
11
#2640000
01
03
#2645000
11
#2650000
01
13
#2655000
11
#2660000
01
03
#2665000
11
#2670000
01
13
#2675000
11
#2680000
01
03
#2685000
11
#2690000
01
13
#2695000
11
#2700000
01
03
#2705000
11
#2710000
01
13
#2715000
11
#2720000
01
03
#2725000
11
#2730000
01
13
#2735000
11
#2740000
01
03
#2745000
11
#2750000
01
13
#2755000
11
#2760000
01
03
#2765000
11
#2770000
01
13
#2775000
11
#2780000
01
03
#2785000
11
#2790000
01
13
#2795000
11
#2800000
01
03
15
#2805000
11
#2810000
01
13
#2815000
11
#2820000
01
03
#2825000
11
#2830000
01
13
1A
1B
#2835000
11
#2840000
01
03
#2845000
11
#2850000
01
13
0A
#2855000
11
#2860000
01
03
#2865000
11
#2870000
01
13
#2875000
11
#2880000
01
03
#2885000
11
#2890000
01
13
#2895000
11
#2900000
01
03
#2905000
11
#2910000
01
13
#2915000
11
#2920000
01
03
#2925000
11
#2930000
01
13
#2935000
11
#2940000
01
03
#2945000
11
#2950000
01
13
#2955000
11
#2960000
01
03
#2965000
11
#2970000
01
13
#2975000
11
#2980000
01
03
#2985000
11
#2990000
01
13
#2995000
11
#3000000
01
03
#3005000
11
#3010000
01
13
#3015000
11
#3020000
01
03
#3025000
11
#3030000
01
13
#3035000
11
#3040000
01
03
#3045000
11
#3050000
01
13
#3055000
11
#3060000
01
03
#3065000
11
#3070000
01
13
#3075000
11
#3080000
01
03
#3085000
11
#3090000
01
13
#3095000
11
#3100000
01
03
#3105000
11
#3110000
01
13
#3115000
11
#3120000
01
03
05
#3125000
11
#3130000
01
13
#3135000
11
#3140000
01
03
#3145000
11
#3150000
01
13
1A
0B
#3155000
11
#3160000
01
03
#3165000
11
#3170000
01
13
0A
#3175000
11
#3180000
01
03
#3185000
11
#3190000
01
13
#3195000
11
#3200000
01
03
#3205000
11
#3210000
01
13
#3215000
11
#3220000
01
03
#3225000
11
#3230000
01
13
#3235000
11
#3240000
01
03
#3245000
11
#3250000
01
13
#3255000
11
#3260000
01
03
#3265000
11
#3270000
01
13
#3275000
11
#3280000
01
03
#3285000
11
#3290000
01
13
#3295000
11
#3300000
01
03
#3305000
11
#3310000
01
13
#3315000
11
#3320000
01
03
#3325000
11
#3330000
01
13
#3335000
11
#3340000
01
03
#3345000
11
#3350000
01
13
#3355000
11
#3360000
01
03
#3365000
11
#3370000
01
13
#3375000
11
#3380000
01
03
#3385000
11
#3390000
01
13
#3395000
11
#3400000
01
03
#3405000
11
#3410000
01
13
#3415000
11
#3420000
01
03
#3425000
11
#3430000
01
13
#3435000
11
#3440000
01
03
#3445000
11
#3450000
01
13
#3455000
11
#3460000
01
03
#3465000
11
#3470000
01
13
1A
#3475000
11
1>
#3480000
01
03
#3485000
11
0>
#3490000
01
13
0A
#3495000
11
#3500000
01
03
#3505000
11
#3510000
01
13
#3515000
11
#3520000
01
03
#3525000
11
#3530000
01
13
#3535000
11
#3540000
01
03
#3545000
11
#3550000
01
13
#3555000
11
#3560000
01
03
#3565000
11
#3570000
01
13
#3575000
11
#3580000
01
03
#3585000
11
#3590000
01
13
#3595000
11
#3600000
01
03
#3605000
11
#3610000
01
13
#3615000
11
#3620000
01
03
#3625000
11
#3630000
01
13
#3635000
11
#3640000
01
03
#3645000
11
#3650000
01
13
#3655000
11
#3660000
01
03
#3665000
11
#3670000
01
13
#3675000
11
#3680000
01
03
#3685000
11
#3690000
01
13
#3695000
11
#3700000
01
03
#3705000
11
#3710000
01
13
#3715000
11
#3720000
01
03
#3725000
11
#3730000
01
13
#3735000
11
#3740000
01
03
#3745000
11
#3750000
01
13
#3755000
11
#3760000
01
03
15
#3765000
11
#3770000
01
13
#3775000
11
#3780000
01
03
#3785000
11
#3790000
01
13
1A
1B
#3795000
11
#3800000
01
03
#3805000
11
#3810000
01
13
0A
#3815000
11
#3820000
01
03
#3825000
11
#3830000
01
13
#3835000
11
#3840000
01
03
#3845000
11
#3850000
01
13
#3855000
11
#3860000
01
03
#3865000
11
#3870000
01
13
#3875000
11
#3880000
01
03
#3885000
11
#3890000
01
13
#3895000
11
#3900000
01
03
#3905000
11
#3910000
01
13
#3915000
11
#3920000
01
03
#3925000
11
#3930000
01
13
#3935000
11
#3940000
01
03
#3945000
11
#3950000
01
13
#3955000
11
#3960000
01
03
#3965000
11
#3970000
01
13
#3975000
11
#3980000
01
03
#3985000
11
#3990000
01
13
#3995000
11
#4000000
01
03
#4005000
11
#4010000
01
13
#4015000
11
#4020000
01
03
#4025000
11
#4030000
01
13
#4035000
11
#4040000
01
03
#4045000
11
#4050000
01
13
#4055000
11
#4060000
01
03
#4065000
11
#4070000
01
13
#4075000
11
#4080000
01
03
#4085000
11
#4090000
01
13
#4095000
11
#4100000
01
03
#4105000
11
#4110000
01
13
1A
#4115000
11
#4120000
01
03
#4125000
11
#4130000
01
13
0A
#4135000
11
#4140000
01
03
#4145000
11
#4150000
01
13
#4155000
11
#4160000
01
03
#4165000
11
#4170000
01
13
#4175000
11
#4180000
01
03
#4185000
11
#4190000
01
13
#4195000
11
#4200000
01
03
#4205000
11
#4210000
01
13
#4215000
11
#4220000
01
03
#4225000
11
#4230000
01
13
#4235000
11
#4240000
01
03
#4245000
11
#4250000
01
13
#4255000
11
#4260000
01
03
#4265000
11
#4270000
01
13
#4275000
11
#4280000
01
03
#4285000
11
#4290000
01
13
#4295000
11
#4300000
01
03
#4305000
11
#4310000
01
13
#4315000
11
#4320000
01
03
#4325000
11
#4330000
01
13
#4335000
11
#4340000
01
03
#4345000
11
#4350000
01
13
#4355000
11
#4360000
01
03
#4365000
11
#4370000
01
13
#4375000
11
#4380000
01
03
#4385000
11
#4390000
01
13
#4395000
11
#4400000
01
03
#4405000
11
#4410000
01
13
#4415000
11
#4420000
01
03
#4425000
11
#4430000
01
13
1A
#4435000
11
#4440000
01
03
#4445000
11
#4450000
01
13
0A
#4455000
11
#4460000
01
03
#4465000
11
#4470000
01
13
#4475000
11
#4480000
01
03
#4485000
11
#4490000
01
13
#4495000
11
#4500000
01
03
#4505000
11
#4510000
01
13
#4515000
11
#4520000
01
03
#4525000
11
#4530000
01
13
#4535000
11
#4540000
01
03
#4545000
11
#4550000
01
13
#4555000
11
#4560000
01
03
#4565000
11
#4570000
01
13
#4575000
11
#4580000
01
03
#4585000
11
#4590000
01
13
#4595000
11
#4600000
01
03
#4605000
11
#4610000
01
13
#4615000
11
#4620000
01
03
#4625000
11
#4630000
01
13
#4635000
11
#4640000
01
03
#4645000
11
#4650000
01
13
#4655000
11
#4660000
01
03
#4665000
11
#4670000
01
13
#4675000
11
#4680000
01
03
#4685000
11
#4690000
01
13
#4695000
11
#4700000
01
03
#4705000
11
#4710000
01
13
#4715000
11
#4720000
01
03
#4725000
11
#4730000
01
13
#4735000
11
#4740000
01
03
#4745000
11
#4750000
01
13
1A
#4755000
11
#4760000
01
03
#4765000
11
#4770000
01
13
0A
#4775000
11
#4780000
01
03
#4785000
11
#4790000
01
13
#4795000
11
#4800000
01
03
#4805000
11
#4810000
01
13
#4815000
11
#4820000
01
03
#4825000
11
#4830000
01
13
#4835000
11
#4840000
01
03
#4845000
11
#4850000
01
13
#4855000
11
#4860000
01
03
#4865000
11
#4870000
01
13
#4875000
11
#4880000
01
03
#4885000
11
#4890000
01
13
#4895000
11
#4900000
01
03
#4905000
11
#4910000
01
13
#4915000
11
#4920000
01
03
#4925000
11
#4930000
01
13
#4935000
11
#4940000
01
03
#4945000
11
#4950000
01
13
#4955000
11
#4960000
01
03
#4965000
11
#4970000
01
13
#4975000
11
#4980000
01
03
#4985000
11
#4990000
01
13
#4995000
11
#5000000
01
03
